tests/__init__.py
zenmai/__init__.py
zenmai/__main__.py
zenmai/cmd.py
zenmai/compile.py
zenmai/decorators.py
zenmai/driver.py
zenmai/langhelpers.py
zenmai/loader.py
zenmai/naming.py
zenmai/utils.py
zenmai/actions/__init__.py
zenmai/actions/concat.py
zenmai/actions/counter.py
zenmai/actions/dynamic.py
zenmai/actions/format.py
zenmai/actions/from_.py
zenmai/actions/get.py
zenmai/actions/import_.py
zenmai/actions/inherit.py
zenmai/actions/jinja2.py
zenmai/actions/load.py
zenmai/actions/partial.py
zenmai/actions/suffix.py
zenmai/core/__init__.py
zenmai/core/context.py
zenmai/core/evaluator.py
zenmai/core/loader.py
zenmai-0.3.0.dist-info/DESCRIPTION.rst
zenmai-0.3.0.dist-info/entry_points.txt
zenmai-0.3.0.dist-info/METADATA
zenmai-0.3.0.dist-info/metadata.json
zenmai-0.3.0.dist-info/RECORD
zenmai-0.3.0.dist-info/top_level.txt
zenmai-0.3.0.dist-info/WHEEL
