Metadata-Version: 2.0
Name: zenmai
Version: 0.3.0
Summary: toy language on yaml or json
Home-page: https://github.com/podhmo/zenmai
Author: podhmo
Author-email: ababjam61+github@gmail.com
License: UNKNOWN
Keywords: yaml,json,toylang,minilang
Platform: UNKNOWN
Classifier: Programming Language :: Python
Classifier: Programming Language :: Python :: Implementation :: CPython
Requires-Dist: dictknife[load]
Requires-Dist: magicalimport
Requires-Dist: jinja2
Requires-Dist: colorama
Provides-Extra: docs
Provides-Extra: testing
